ca3/__init__.py
ca3/classical.py
ca3/frequency.py
ca3/helpers.py
ca3/modern.py
cryptanalib3-1.0.0b0.dist-info/LICENSE
cryptanalib3-1.0.0b0.dist-info/METADATA
cryptanalib3-1.0.0b0.dist-info/WHEEL
cryptanalib3-1.0.0b0.dist-info/top_level.txt
cryptanalib3-1.0.0b0.dist-info/zip-safe
cryptanalib3-1.0.0b0.dist-info/RECORD
