Metadata-Version: 2.1
Name: cryptanalib3
Version: 1.0.0b0
Summary: A Python3 fork of the Cryptanalib cryptanalysis module from FeatherDuster
Home-page: http://github.com/unicornsasfuel/cryptanalib3
Author: Daniel "unicornfurnace" Crowley
License: BSD
Platform: UNKNOWN
Classifier: Programming Language :: Python :: 3
Classifier: Operating System :: OS Independent
Requires-Python: >=3.6
Requires-Dist: pycryptodome
